pdf2ppt/__init__.py
pdf2ppt/pdf2ppt.py
pdf2ppt/version.py
pdf2ppt-0.0.2.dist-info/METADATA
pdf2ppt-0.0.2.dist-info/WHEEL
pdf2ppt-0.0.2.dist-info/entry_points.txt
pdf2ppt-0.0.2.dist-info/top_level.txt
pdf2ppt-0.0.2.dist-info/RECORD
